sensoridRequest/sensoridRequest.py
sensoridRequest/__init__.py
sensoridRequest-1.0.4.dist-info/DESCRIPTION.rst
sensoridRequest-1.0.4.dist-info/top_level.txt
sensoridRequest-1.0.4.dist-info/metadata.json
sensoridRequest-1.0.4.dist-info/RECORD
sensoridRequest-1.0.4.dist-info/WHEEL
sensoridRequest-1.0.4.dist-info/METADATA
