Metadata-Version: 2.0
Name: sensoridRequest
Version: 1.0.4
Summary: Proof of concept packaged installer for carbon black with extended functionality',
Requires-Dist: cbapi
Requires-Dist: simplejson
Requires-Dist: requests
Requires-Dist: urllib3
